bare68k/__init__.py
bare68k/consts.py
bare68k/cpucfg.py
bare68k/errors.py
bare68k/handler.py
bare68k/label.py
bare68k/machine.cp36-win32.pyd
bare68k/memcfg.py
bare68k/runcfg.py
bare68k/runtime.py
bare68k/api/__init__.py
bare68k/api/_getmach.py
bare68k/api/cpu.py
bare68k/api/disasm.py
bare68k/api/label.py
bare68k/api/machine.py
bare68k/api/mem.py
bare68k/api/tools.py
bare68k/api/traps.py
bare68k/debug/__init__.py
bare68k/debug/cpusnapshot.py
bare68k/debug/disassemble.py
bare68k/debug/regdump.py
bare68k-0.1.2.dist-info/DESCRIPTION.rst
bare68k-0.1.2.dist-info/METADATA
bare68k-0.1.2.dist-info/RECORD
bare68k-0.1.2.dist-info/WHEEL
bare68k-0.1.2.dist-info/metadata.json
bare68k-0.1.2.dist-info/top_level.txt
