Metadata-Version: 2.0
Name: bare68k
Version: 0.1.2
Summary: A package to create m68k system emulators
Home-page: http://github.com/cnvogelg/bare68k
Author: Christian Vogelgsang
Author-email: chris@vogelgsang.org
License: License :: OSI Approved :: GNU General Public License v2 (GPLv2)
Platform: UNKNOWN
Classifier: Development Status :: 4 - Beta
Classifier: Intended Audience :: Developers
Classifier: Programming Language :: Cython
Classifier: Programming Language :: C
Classifier: Programming Language :: Python
Classifier: Programming Language :: Python :: 2
Classifier: Programming Language :: Python :: 2.7
Classifier: Programming Language :: Python :: 3
Classifier: Programming Language :: Python :: 3.4
Classifier: Programming Language :: Python :: 3.5
Classifier: Programming Language :: Python :: 3.6
Classifier: Programming Language :: Python :: Implementation :: CPython
Classifier: Topic :: System :: Emulators
Requires-Dist: future
